fastapi_kit/__init__.py
fastapi_kit/auth.py
fastapi_kit/exception.py
fastapi_kit/permission.py
fastapi_kit/schema.py
fastapi_kit/utils.py
fastapi_kit-0.1.5.dist-info/METADATA
fastapi_kit-0.1.5.dist-info/WHEEL
fastapi_kit-0.1.5.dist-info/RECORD
